adalib/__init__.py
adalib/adaboard/__init__.py
adalib/adaboard/adaboard.py
adalib/apps/__init__.py
adalib/apps/apps.py
adalib/cards/__init__.py
adalib/cards/cards.py
adalib/exceptions.py
adalib/harbor/__init__.py
adalib/harbor/harbor.py
adalib/issues/__init__.py
adalib/issues/issues.py
adalib/keywords/__init__.py
adalib/keywords/keywords.py
adalib/lab/__init__.py
adalib/lab/lab.py
adalib/pictures/__init__.py
adalib/pictures/pictures.py
adalib/schedules/__init__.py
adalib/schedules/schedules.py
adalib/superset/__init__.py
adalib/superset/client.py
adalib/utils/__init__.py
adalib/utils/acl.py
adalib/utils/volumes.py
adalib/volumes/__init__.py
adalib/volumes/volumes.py
adalib-9.0.0.dist-info/METADATA
adalib-9.0.0.dist-info/WHEEL
adalib-9.0.0.dist-info/RECORD
