Metadata-Version: 2.4
Name: adalib
Version: 9.0.0
Summary: Python API for the AdaLab environment
Keywords: documentation,pep621,mkdocs,toml
Author: Adamatics
Author-email: info@adamatics.com
Requires-Python: >=3.10.0,<4.0.0
Classifier: Development Status :: 5 - Production/Stable
Classifier: Intended Audience :: Developers
Classifier: Operating System :: OS Independent
Classifier: Programming Language :: Python
Classifier: Programming Language :: Python :: 3
Classifier: Programming Language :: Python :: 3.10
Classifier: Programming Language :: Python :: 3.11
Classifier: Programming Language :: Python :: 3.12
Classifier: Programming Language :: Python :: 3.13
Classifier: Programming Language :: Python :: 3.14
Classifier: Topic :: Software Development :: Libraries :: Python Modules
Classifier: Typing :: Typed
Requires-Dist: adalib-auth (>=1.2.2)
Requires-Dist: pandas (>=1.0.0)
Requires-Dist: requests (>=2.31.0)
Requires-Dist: requests-oauthlib (>=1.3.0)
Requires-Dist: superset-api-client (>=0.6.0)
Project-URL: Documentation, https://adalib.adamatics.com/docs/latest/
Project-URL: Homepage, https://adamatics.com
Project-URL: Repository, https://gitlab.com/adamatics/python/adalib
